TestPrimeEngine/__init__.py
TestPrimeEngine/cache_engine.py
TestPrimeEngine/symbolic_factoring.py
TestPrimeEngine/warm_cache.py
testprimeengine-0.1.1.dist-info/METADATA
testprimeengine-0.1.1.dist-info/WHEEL
testprimeengine-0.1.1.dist-info/top_level.txt
testprimeengine-0.1.1.dist-info/RECORD
