Metadata-Version: 2.4
Name: testprimeengine
Version: 0.1.1
Summary: PrimeEngineAI TestPrimeEngine package
Author: Lee Bond
Author-email: leebo@example.com
Requires-Python: >=3.7
Dynamic: author
Dynamic: author-email
Dynamic: description
Dynamic: description-content-type
Dynamic: requires-python
Dynamic: summary
